{
    "client": "Thunder Client",
    "collectionName": "Telescope Control",
    "dateExported": "2023-12-12T15:21:14.520Z",
    "version": "1.1",
    "folders": [],
    "requests": [
        {
            "_id": "9086220d-fe44-48ef-b756-b6d2712b2d3b",
            "colId": "a934c085-9147-4c93-8899-503573da9ad3",
            "containerId": "",
            "name": "Calibrate - Solar System Object",
            "url": "{{API_URL}}/calibrate/solar_system_object/?name=jupiter",
            "method": "POST",
            "sortNum": 10000,
            "created": "2023-12-12T05:01:56.256Z",
            "modified": "2023-12-12T05:01:56.256Z",
            "headers": [],
            "params": [
                {
                    "name": "name",
                    "value": "jupiter",
                    "isPath": false
                }
            ],
            "tests": []
        },
        {
            "_id": "bce89f57-9d7e-45ee-b5de-050dac719eb3",
            "colId": "a934c085-9147-4c93-8899-503573da9ad3",
            "containerId": "",
            "name": "Calibrate - By Object Name",
            "url": "{{API_URL}}/calibrate/by_name/?name=polaris",
            "method": "POST",
            "sortNum": 20000,
            "created": "2023-12-12T05:01:56.257Z",
            "modified": "2023-12-12T05:01:56.257Z",
            "headers": [],
            "params": [
                {
                    "name": "name",
                    "value": "polaris",
                    "isPath": false
                }
            ],
            "tests": []
        },
        {
            "_id": "97002266-2a65-4a3f-9859-dd09abc70a56",
            "colId": "a934c085-9147-4c93-8899-503573da9ad3",
            "containerId": "",
            "name": "Calibrate - By RA / Dec",
            "url": "{{API_URL}}/calibrate/?ra=00h45m42.223s&dec=37d56m33.427s",
            "method": "POST",
            "sortNum": 30000,
            "created": "2023-12-12T05:01:56.258Z",
            "modified": "2023-12-12T05:01:56.258Z",
            "headers": [],
            "params": [
                {
                    "name": "ra",
                    "value": "00h45m42.223s",
                    "isPath": false
                },
                {
                    "name": "dec",
                    "value": "37d56m33.427s",
                    "isPath": false
                }
            ],
            "tests": []
        },
        {
            "_id": "d31e92e1-46fe-40d2-8b21-6b8d5519b5d7",
            "colId": "a934c085-9147-4c93-8899-503573da9ad3",
            "containerId": "",
            "name": "Goto - By Object Name",
            "url": "{{API_URL}}/goto/by_name?name=jupiter",
            "method": "POST",
            "sortNum": 40000,
            "created": "2023-12-12T05:01:56.260Z",
            "modified": "2023-12-12T05:01:56.260Z",
            "headers": [],
            "params": [
                {
                    "name": "name",
                    "value": "jupiter",
                    "isPath": false
                }
            ],
            "tests": []
        },
        {
            "_id": "1fb9b548-9d10-433b-a037-8313ee77b6e8",
            "colId": "a934c085-9147-4c93-8899-503573da9ad3",
            "containerId": "",
            "name": "Goto - Solar System Object",
            "url": "{{API_URL}}/goto/solar_system_object/?name=saturn",
            "method": "POST",
            "sortNum": 50000,
            "created": "2023-12-12T05:01:56.261Z",
            "modified": "2023-12-12T06:33:54.449Z",
            "headers": [],
            "params": [
                {
                    "name": "name",
                    "value": "saturn",
                    "isPath": false
                }
            ],
            "tests": []
        },
        {
            "_id": "1bb9b2d7-21a7-4f5c-84b1-a5fa24a5a946",
            "colId": "a934c085-9147-4c93-8899-503573da9ad3",
            "containerId": "",
            "name": "Goto - RA / Dec",
            "url": "{{API_URL}}/goto/?ra=00h45m42.223s&dec=37d56m33.427s",
            "method": "POST",
            "sortNum": 60000,
            "created": "2023-12-12T05:01:56.259Z",
            "modified": "2023-12-12T05:01:56.259Z",
            "headers": [],
            "params": [
                {
                    "name": "ra",
                    "value": "00h45m42.223s",
                    "isPath": false
                },
                {
                    "name": "dec",
                    "value": "37d56m33.427s",
                    "isPath": false
                }
            ],
            "tests": []
        }
    ]
}